wayremap/__init__.py
wayremap/config.py
wayremap/constants.py
wayremap/ecodes.py
wayremap/i3ipc-test.py
wayremap/main.py
wayremap/os-test.py
wayremap-0.0.10.dist-info/LICENSE
wayremap-0.0.10.dist-info/WHEEL
wayremap-0.0.10.dist-info/METADATA
wayremap-0.0.10.dist-info/RECORD
