Metadata-Version: 2.1
Name: wayremap
Version: 0.0.10
Summary: A dynamic keyboard remapper for Wayland.
Home-page: https://github.com/acro5piano/wayremap
License: MIT
Author: Kay Gosho
Author-email: ketsume0211@gmail.com
Requires-Python: >=3.9,<4.0
Classifier: License :: OSI Approved :: MIT License
Classifier: Programming Language :: Python :: 3
Classifier: Programming Language :: Python :: 3.10
Classifier: Programming Language :: Python :: 3.9
Requires-Dist: evdev (>=1.4.0,<2.0.0)
Requires-Dist: i3ipc (>=2.2.1,<3.0.0)
Requires-Dist: python-uinput (>=0.11.2,<0.12.0)
Project-URL: Repository, https://github.com/acro5piano/wayremap
